basex_python-0.1.0.dist-info/WHEEL
basex_python-0.1.0.dist-info/top_level.txt
basex_python-0.1.0.dist-info/METADATA
basex_python-0.1.0.dist-info/RECORD
basex_python-0.1.0.dist-info/licenses/LICENSE
basex/_version.py
basex/constants.py
basex/presets.py
basex/basex.py
basex/modes.py
basex/_basex.pyx
basex/_basex.c
basex/_basex.cpython-312-aarch64-linux-gnu.so
basex/__init__.py
