Metadata-Version: 2.4
Name: basex-python
Version: 0.1.0
Summary: Fast library for encoding/decoding data in custom base-N alphabets of any size
Author: yokotoka
License: MIT
Project-URL: Homepage, https://github.com/yokotoka/basex
Project-URL: Repository, https://github.com/yokotoka/basex
Keywords: base58,base64,base32,base16,encoding,decoding,baseN
Classifier: Development Status :: 4 - Beta
Classifier: Intended Audience :: Developers
Classifier: License :: OSI Approved :: MIT License
Classifier: Programming Language :: Python :: 3
Classifier: Programming Language :: Python :: 3.10
Classifier: Programming Language :: Python :: 3.11
Classifier: Programming Language :: Python :: 3.12
Classifier: Programming Language :: Python :: 3.13
Classifier: Programming Language :: Python :: 3.14
Classifier: Topic :: Software Development :: Libraries :: Python Modules
Classifier: Topic :: Security :: Cryptography
Requires-Python: <3.15,>=3.10
License-File: LICENSE
Dynamic: license-file
